{
  "dts": {
    "sys": {
      "white": {
        "value": "#ffffff",
        "type": "color"
      },
      "black": {
        "value": "#000000",
        "type": "color"
      },
      "blue": {
        "value": "#0000ff",
        "type": "color"
      },
      "red": {
        "value": "#ff0000",
        "type": "color"
      }
    },
    "body": {
      "large": {
        "fontFamily": {
          "value": "Roboto",
          "type": "fontFamilies"
        },
        "fontWeight": {
          "value": "Regular",
          "type": "fontWeights"
        },
        "lineHeight": {
          "value": 24,
          "type": "lineHeights"
        },
        "fontSize": {
          "value": 16,
          "type": "fontSizes"
        },
        "letterSpacing": {
          "value": "0%",
          "type": "letterSpacing"
        },
        "paragraphSpacing": {
          "value": 0,
          "type": "paragraphSpacing"
        },
        "paragraphIndent": {
          "value": "0px",
          "type": "paragraphIndent"
        },
        "textCase": {
          "value": "none",
          "type": "textCase"
        },
        "textDecoration": {
          "value": "none",
          "type": "textDecoration"
        }
      }
    }
  },
  "fontFamilies": {
    "roboto": {
      "value": "Roboto",
      "type": "fontFamilies"
    }
  },
  "lineHeights": {
    "0": {
      "value": 24,
      "type": "lineHeights"
    }
  },
  "fontWeights": {
    "roboto-0": {
      "value": "Regular",
      "type": "fontWeights"
    }
  },
  "fontSize": {
    "0": {
      "value": 16,
      "type": "fontSizes"
    }
  },
  "letterSpacing": {
    "0": {
      "value": "0%",
      "type": "letterSpacing"
    }
  },
  "paragraphSpacing": {
    "0": {
      "value": 0,
      "type": "paragraphSpacing"
    }
  },
  "textCase": {
    "none": {
      "value": "none",
      "type": "textCase"
    }
  },
  "textDecoration": {
    "none": {
      "value": "none",
      "type": "textDecoration"
    }
  },
  "paragraphIndent": {
    "0": {
      "value": "0px",
      "type": "dimension"
    }
  },
  "tokenSetOrder": {
    "0": {
      "value": "dts",
      "type": "other"
    }
  }
}